masureel/__init__.py
masureel/console.py
masureel/data/agathe.xlsx
masureel/data/cabinet.xlsx
masureel/data/collections.json
masureel/data/database.csv
masureel/data/Dict.csv
masureel/data/kimono.xlsx
masureel/data/orbital.xlsx
masureel/data/shaders.json
masureel/data.py
masureel/excel.py
masureel/max/shaderlist.py
masureel/product.py
masureel/topviews.py
masureel/translate.py
masureel-0.1.9.8.dist-info/entry_points.txt
masureel-0.1.9.8.dist-info/WHEEL
masureel-0.1.9.8.dist-info/METADATA
masureel-0.1.9.8.dist-info/RECORD
